{
  "schemaVersion": 1,
  "id": "modid",
  "version": "${version}",

  "name": "Ores Extended",
  "description": "A vanilla Minecraft Ore, Item, and Tool enhancement",
  "authors": [
    "Me!"
  ],
  "contact": {
    "homepage": "https://www.oresextended.com",
    "sources": "https://github.com/jeff-moon/OresExtended"
  },

  "license": "CC0-1.0",
  "icon": "assets/modid/icon.png",

  "environment": "*",
  "entrypoints": {
    "main": [
      "com.oresextended.entry.OresExtended"
    ]
  },
  "mixins": [
    "modid.mixins.json"
  ],

  "depends": {
    "fabricloader": ">=0.11.3",
    "fabric": "*",
    "minecraft": "1.17.x",
    "java": ">=16"
  },
  "suggests": {
    "another-mod": "*"
  }
}
